smathbyviraj/__init__.py
smathbyviraj/smathbyvirajcode.py
smathbyviraj-0.6.2.dist-info/licenses/LICENSE
smathbyviraj-0.6.2.dist-info/METADATA
smathbyviraj-0.6.2.dist-info/WHEEL
smathbyviraj-0.6.2.dist-info/top_level.txt
smathbyviraj-0.6.2.dist-info/RECORD
