Metadata-Version: 2.4
Name: smathbyviraj
Version: 0.6.2
Summary: Simple math utilities by Viraj
Author: Viraj
License: MIT
Classifier: Programming Language :: Python :: 3
Classifier: Operating System :: OS Independent
Requires-Python: >=3.6
License-File: LICENSE
Dynamic: author
Dynamic: classifier
Dynamic: license
Dynamic: license-file
Dynamic: requires-python
Dynamic: summary
